chemlistem/__init__.py
chemlistem/chebinames.txt
chemlistem/chebiobo.py
chemlistem/corpusreader.py
chemlistem/elements.txt
chemlistem/ensemblemodel.py
chemlistem/extract_rf.py
chemlistem/featurizer.py
chemlistem/minimodel.py
chemlistem/tradmodel.py
chemlistem/utils.py
chemlistem/words.txt
chemtok/ChemTokeniser.py
chemtok/HyphenTokeniser.py
chemtok/SentenceSplitter.py
chemtok/StringTools.py
chemtok/Token.py
chemtok/__init__.py
ChemListem-0.1.0.dist-info/METADATA
ChemListem-0.1.0.dist-info/WHEEL
ChemListem-0.1.0.dist-info/top_level.txt
ChemListem-0.1.0.dist-info/RECORD
