Metadata-Version: 2.1
Name: ChemListem
Version: 0.1.0
Summary: Chemical Named Entity Recognition using Deep Learning
Home-page: https://bitbucket.org/rscapplications/chemlistem
Author: Peter Corbett
Author-email: corbettp@rsc.org
License: MIT
Platform: UNKNOWN
Requires-Dist: keras (>=2.0.3)
Requires-Dist: scikit-learn
Requires-Dist: numpy
Requires-Dist: h5py
